{
	"name": "DestinationDataset_a3b",
	"properties": {
		"linkedServiceName": {
			"referenceName": "AzureBlobStorage2_Destination",
			"type": "LinkedServiceReference"
		},
		"annotations": [],
		"type": "DelimitedText",
		"typeProperties": {
			"location": {
				"type": "AzureBlobStorageLocation",
				"container": "refined"
			},
			"columnDelimiter": ",",
			"rowDelimiter": "\n",
			"escapeChar": "\\",
			"firstRowAsHeader": true,
			"quoteChar": "\""
		},
		"schema": []
	},
	"type": "Microsoft.DataFactory/factories/datasets"
}